Metadata-Version: 1.0
Name: uamd
Version: 0.1rc4
Summary: User Agent Mobile Detect
Home-page: https://github.com/lambdalisue/uamd
Author: Alisue
Author-email: lambdalisue@hashnote.net
License: BSD
Download-URL: https://github.com/lambdalisue/uamd/tarball/master
Keywords: mobile detect HTTP_USER_AGENT user_agent
Platform: UNKNOWN
Classifier: Intended Audience :: Developers
Classifier: License :: OSI Approved :: BSD License
Classifier: Programming Language :: Python
Classifier: Topic :: Internet :: WWW/HTTP
